.gitignore
.travis.yml
Dockerfile
LICENSE
MANIFEST.in
README.md
env.yaml
pyproject.toml
requirements.txt
setup.py
cemba_data/__init__.py
cemba_data/__main__.py
cemba_data/_version.py
cemba_data/_yap_internal_cli_.py
cemba_data/qsub.py
cemba_data/sbatch.py
cemba_data/utilities.py
cemba_data.egg-info/PKG-INFO
cemba_data.egg-info/SOURCES.txt
cemba_data.egg-info/dependency_links.txt
cemba_data.egg-info/entry_points.txt
cemba_data.egg-info/requires.txt
cemba_data.egg-info/top_level.txt
cemba_data/bulk/__init__.py
cemba_data/bulk/atac_bulk.py
cemba_data/bulk/mc_bulk.py
cemba_data/bulk/mct_bulk.py
cemba_data/bulk/Snakefile_template/__init__.py
cemba_data/bulk/Snakefile_template/mc_bulk.Snakefile
cemba_data/bulk/mc_bulk_multigroup/__init__.py
cemba_data/bulk/mc_bulk_multigroup/mc_bulk_multigroup.py
cemba_data/bulk/mc_bulk_multigroup/mc_bulk_multigroup_template.py
cemba_data/demultiplex/__init__.py
cemba_data/demultiplex/demultiplex.py
cemba_data/demultiplex/fastq_dataframe.py
cemba_data/demultiplex/plateinfo_and_samplesheet.py
cemba_data/dmr/__init__.py
cemba_data/dmr/dmrseq/DMRseq.ipynb
cemba_data/dmr/dmrseq/__init__.py
cemba_data/dmr/dss/DSS.MultiGroup.SingleRegionDML.ipynb
cemba_data/dmr/dss/DSS.TwoGroup.SingleRegionDML.ipynb
cemba_data/dmr/dss/MultiGroup.py
cemba_data/dmr/dss/TwoGroup.py
cemba_data/dmr/dss/__init__.py
cemba_data/files/V1_i7_i5_index.tsv
cemba_data/files/V2_i7_i5_index.tsv
cemba_data/files/__init__.py
cemba_data/files/plate_info_template_v1.txt
cemba_data/files/plate_info_template_v2.txt
cemba_data/files/random_index_v1.fa
cemba_data/files/sample_sheet_header.txt
cemba_data/files/sbatch_template_schicluster.txt
cemba_data/files/sbatch_template_yap.txt
cemba_data/files/default_config/__init__.py
cemba_data/files/default_config/mapping_config_4m.ini
cemba_data/files/default_config/mapping_config_m3c.ini
cemba_data/files/default_config/mapping_config_mc.ini
cemba_data/files/default_config/mapping_config_mct-nome.ini
cemba_data/files/default_config/mapping_config_mct.ini
cemba_data/files/default_config/mapping_config_nome.ini
cemba_data/files/mapping_summary_template/4m_template.ipynb
cemba_data/files/mapping_summary_template/__init__.py
