Metadata-Version: 2.1
Name: cemba-data
Version: 1.6.5
Summary: Pipelines for single nucleus methylome and multi-omic dataset.
Home-page: https://github.com/lhqing/cemba_data
Author: Hanqing Liu
Author-email: hanliu@salk.edu
License: MIT
Classifier: License :: OSI Approved :: MIT License
Classifier: Programming Language :: Python :: 3
Classifier: Programming Language :: Python :: 3.7
License-File: LICENSE
